clw/__about__.py
clw/__init__.py
clw/__main__.py
clw/app.py
clw/iconset.py
clw/weather.py
clw/widgets.py
clw/resources/openweathermap-codes.json
clw/resources/png/clear-day.png
clw/resources/png/clear-night.png
clw/resources/png/cloudy.png
clw/resources/png/drizzle.png
clw/resources/png/extreme-day-drizzle.png
clw/resources/png/extreme-day-fog.png
clw/resources/png/extreme-day-rain.png
clw/resources/png/extreme-day-snow.png
clw/resources/png/extreme-drizzle.png
clw/resources/png/extreme-night-drizzle.png
clw/resources/png/extreme-night-fog.png
clw/resources/png/extreme-night-rain.png
clw/resources/png/extreme-night-snow.png
clw/resources/png/fog-day.png
clw/resources/png/fog-night.png
clw/resources/png/overcast-day-drizzle.png
clw/resources/png/overcast-day-rain.png
clw/resources/png/overcast-day-sleet.png
clw/resources/png/overcast-day-snow.png
clw/resources/png/overcast-night-drizzle.png
clw/resources/png/overcast-night-rain.png
clw/resources/png/overcast-night-sleet.png
clw/resources/png/overcast-night-snow.png
clw/resources/png/overcast-rain.png
clw/resources/png/partly-cloudy-day-drizzle.png
clw/resources/png/partly-cloudy-day-rain.png
clw/resources/png/partly-cloudy-day-sleet.png
clw/resources/png/partly-cloudy-day-snow.png
clw/resources/png/partly-cloudy-day.png
clw/resources/png/partly-cloudy-night-drizzle.png
clw/resources/png/partly-cloudy-night-rain.png
clw/resources/png/partly-cloudy-night-sleet.png
clw/resources/png/partly-cloudy-night-snow.png
clw/resources/png/partly-cloudy-night.png
clw/resources/png/snowflake.png
clw/resources/png/thunderstorms-day-extreme-snow.png
clw/resources/png/thunderstorms-day-overcast-snow.png
clw/resources/png/thunderstorms-day.png
clw/resources/png/thunderstorms-night-extreme-snow.png
clw/resources/png/thunderstorms-night-overcast-snow.png
clw/resources/png/thunderstorms-night.png
clw/resources/png/weather-codes.json
acme_weather-0.7.0.dist-info/METADATA
acme_weather-0.7.0.dist-info/WHEEL
acme_weather-0.7.0.dist-info/entry_points.txt
acme_weather-0.7.0.dist-info/licenses/LICENSE
acme_weather-0.7.0.dist-info/RECORD
