Metadata-Version: 2.4
Name: acme-weather
Version: 0.7.0
Summary: Add your description here
Project-URL: Documentation, https://github.com/philion/clw#readme
Project-URL: Issues, https://github.com/philion/clw/issues
Project-URL: Source, https://github.com/philion/clw
License-File: LICENSE
Requires-Python: >=3.13
Requires-Dist: astral>=3.2
Requires-Dist: numpy>=2.2.3
Requires-Dist: openmeteo-requests>=1.3.0
Requires-Dist: pandas>=2.2.3
Requires-Dist: pex>=2.33.1
Requires-Dist: pillow>=10.4.0
Requires-Dist: requests-cache>=1.2.1
Requires-Dist: requests>=2.32.3
Requires-Dist: retry-requests>=2.0.0
Requires-Dist: textual-dev>=1.7.0
Requires-Dist: textual-image>=0.7.0
Requires-Dist: textual>=1.0.0
